Workbook

Sheet Questions
A1: CATHEDRAL CENTER — GROWTH READINESS ASSESSMENT
A2: Tier 2 Self-Assessment | Measures Current Growth Capability vs. Growth Aspiration Across 5 Dimensions
A3: Response Scale: 1 = Not at all like our firm | 2 = Not much like our firm | 3 = Somewhat like our firm | 4 = Mostly like our firm | 5 = Exactly like our firm
A4: # | B4: Growth Dimension | C4: Code | D4: Assessment Statement | E4: Context & Guidance | F4: Current State (1-5) | G4: Growth Target (1-5) | H4: Growth Gap
A5: ORGANIC GROWTH ENGINE
A6: 1 | B6: Organic Growth Engine | C6: OG-01 | D6: Our firm has a clearly defined and documented client acquisition strategy that generates a consistent pipeline of qualified prospective clients aligned with our ideal client profile. | E6: Documented acquisition strategy transforms reactive referral dependency into proactive pipeline management. Firms with systematic acquisition processes grow more predictably and efficiently. | H6: =IF(AND(F6<>"",G6<>""),ABS(G6-F6),"")
A7: 2 | B7: Organic Growth Engine | C7: OG-02 | D7: We maintain an active center-of-influence network with CPAs, attorneys, and other professionals who regularly provide qualified referrals based on genuine understanding of our value proposition. | E7: COI networks represent one of the most cost-effective client acquisition channels. The quality and consistency of these relationships directly correlate with organic growth trajectory. | H7: =IF(AND(F7<>"",G7<>""),ABS(G7-F7),"")
A8: 3 | B8: Organic Growth Engine | C8: OG-03 | D8: Our firm has measurable client retention metrics above 95% annually, and we actively invest in relationship deepening strategies to grow revenue from existing clients. | E8: Client retention is the foundation of organic growth. Firms that lose clients faster than they acquire them face a mathematical growth barrier regardless of acquisition effort. | H8: =IF(AND(F8<>"",G8<>""),ABS(G8-F8),"")
A9: 4 | B9: Organic Growth Engine | C9: OG-04 | D9: We have a structured client review and upsell process that identifies opportunities to expand services, deepen planning engagement, and increase household wallet share within existing relationships. | E9: Revenue expansion within existing clients is the most efficient growth pathway. Structured deepening processes convert service conversations into revenue growth without acquisition costs. | H9: =IF(AND(F9<>"",G9<>""),ABS(G9-F9),"")
A10: 5 | B10: Organic Growth Engine | C10: OG-05 | D10: Our firm actively cultivates a client referral culture where satisfied clients proactively introduce prospective clients, and we have systems to encourage, track, and recognize these referrals. | E10: Client referrals represent the highest-converting, lowest-cost acquisition channel. Firms that systematize referral generation create compounding growth from their existing client base. | H10: =IF(AND(F10<>"",G10<>""),ABS(G10-F10),"")
A11: 6 | B11: Organic Growth Engine | C11: OG-06 | D11: We have defined minimum engagement criteria for new clients — including minimum asset levels, planning complexity, and service expectations — that ensure new relationships are profitable from inception. | E11: Disciplined client selection protects profitability during growth. Firms that accept any client regardless of fit dilute advisor capacity and reduce overall service quality. | H11: =IF(AND(F11<>"",G11<>""),ABS(G11-F11),"")
A12: 7 | B12: Organic Growth Engine | C12: OG-07 | D12: Our firm measures client satisfaction through structured feedback mechanisms such as surveys, Net Promoter Score tracking, or formal review conversations at least annually. | E12: Client satisfaction measurement provides early warning of retention risk and identifies improvement opportunities. Firms that measure satisfaction grow faster because they address issues before they become departures. | H12: =IF(AND(F12<>"",G12<>""),ABS(G12-F12),"")
A13: 8 | B13: Organic Growth Engine | C13: OG-08 | D13: We have a clearly defined ideal client profile that guides all acquisition efforts, including demographic characteristics, asset range, planning needs, and behavioral attributes. | E13: Ideal client clarity focuses resources on the highest-value acquisition targets. Without a defined profile, marketing and business development efforts scatter across unprofitable segments. | H13: =IF(AND(F13<>"",G13<>""),ABS(G13-F13),"")
A14: 9 | B14: Organic Growth Engine | C14: OG-09 | D14: Our firm invests in thought leadership activities — such as speaking engagements, published content, community education, or media presence — that establish our expertise and attract prospective clients. | E14: Thought leadership creates inbound attraction that complements outbound acquisition. Advisors recognized as experts in their market attract higher-quality, more-engaged prospects. | H14: =IF(AND(F14<>"",G14<>""),ABS(G14-F14),"")
A15: 10 | B15: Organic Growth Engine | C15: OG-10 | D15: We track organic growth metrics rigorously, including new client count, net new assets, revenue per client growth, and pipeline conversion rates, and we use this data to refine our growth strategy. | E15: Growth measurement enables growth management. Firms that track leading and lagging growth indicators can diagnose growth issues early and allocate resources to highest-impact activities. | H15: =IF(AND(F15<>"",G15<>""),ABS(G15-F15),"")
A16: INORGANIC GROWTH CAPABILITY
A17: 11 | B17: Inorganic Growth Capability | C17: IG-01 | D17: Our firm has clearly defined its appetite and criteria for acquisitions, including target firm size, geographic focus, service compatibility, and cultural alignment requirements. | E17: Clear acquisition criteria enable efficient deal sourcing and evaluation. Without defined parameters, firms waste time evaluating incompatible opportunities or miss attractive targets. | H17: =IF(AND(F17<>"",G17<>""),ABS(G17-F17),"")
A18: 12 | B18: Inorganic Growth Capability | C18: IG-02 | D18: We have financial capacity — through available capital, financing relationships, or equity recapitalization — to fund acquisition transactions without compromising ongoing business operations. | E18: Financial capacity for acquisitions separates aspirational acquirers from capable ones. Firms that have pre-arranged financing or capital reserves can move quickly when opportunities arise. | H18: =IF(AND(F18<>"",G18<>""),ABS(G18-F18),"")
A19: 13 | B19: Inorganic Growth Capability | C19: IG-03 | D19: Our firm has experience or access to experienced advisors who can guide M&A due diligence, valuation analysis, deal structuring, and post-closing integration processes. | E19: M&A expertise prevents costly mistakes. First-time acquirers who lack experienced counsel frequently overpay, underestimate integration costs, or miss critical due diligence findings. | H19: =IF(AND(F19<>"",G19<>""),ABS(G19-F19),"")
A20: 14 | B20: Inorganic Growth Capability | C20: IG-04 | D20: We have a proven operational integration playbook — including technology migration, client communication, team onboarding, and compliance harmonization — that can be applied to future acquisitions. | E20: Integration capability determines whether acquisition value is realized or destroyed. Firms with repeatable integration processes achieve faster synergy realization and better client retention. | H20: =IF(AND(F20<>"",G20<>""),ABS(G20-F20),"")
A21: 15 | B21: Inorganic Growth Capability | C21: IG-05 | D21: Our firm maintains an active deal pipeline by systematically cultivating relationships with potential acquisition targets, industry intermediaries, and custodial referral programs. | E21: Pipeline development creates acquisition optionality. Firms that cultivate relationships before they need to transact negotiate from a position of choice rather than urgency. | H21: =IF(AND(F21<>"",G21<>""),ABS(G21-F21),"")
A22: 16 | B22: Inorganic Growth Capability | C22: IG-06 | D22: We have the management capacity and bench strength to absorb acquired teams, clients, and operations without material disruption to our existing practice or service quality. | E22: Absorption capacity determines realistic acquisition pace. Firms that overextend management capacity through acquisitions risk degrading service quality across the entire combined entity. | H22: =IF(AND(F22<>"",G22<>""),ABS(G22-F22),"")
A23: 17 | B23: Inorganic Growth Capability | C23: IG-07 | D23: Our technology platform and operational infrastructure can scale to accommodate significant growth from acquisitions without requiring complete system overhauls or major capital investment. | E23: Scalable infrastructure enables efficient acquisition integration. Firms whose systems cannot accommodate growth face compounding technology and operational costs with each acquisition. | H23: =IF(AND(F23<>"",G23<>""),ABS(G23-F23),"")
A24: 18 | B24: Inorganic Growth Capability | C24: IG-08 | D24: We have established cultural assessment and compatibility evaluation processes that inform acquisition decisions beyond financial metrics, reducing the risk of culture clash post-closing. | E24: Cultural due diligence prevents the most common cause of acquisition failure. Firms that evaluate cultural compatibility with the same rigor as financial metrics achieve better long-term outcomes. | H24: =IF(AND(F24<>"",G24<>""),ABS(G24-F24),"")
A25: 19 | B25: Inorganic Growth Capability | C25: IG-09 | D25: Our firm has a clear understanding of current market valuations, deal structures, and competitive dynamics in the advisory firm acquisition landscape. | E25: Market intelligence enables informed deal-making. Firms that understand current valuation trends, competitive buyer landscape, and deal structure norms negotiate better terms. | H25: =IF(AND(F25<>"",G25<>""),ABS(G25-F25),"")
A26: 20 | B26: Inorganic Growth Capability | C26: IG-10 | D26: We have post-acquisition performance measurement systems that track integration progress, client retention, revenue synergies, and team satisfaction to ensure acquired value is preserved. | E26: Integration measurement ensures accountability. Without performance tracking, firms cannot objectively assess whether acquisitions are delivering expected returns on investment. | H26: =IF(AND(F26<>"",G26<>""),ABS(G26-F26),"")
A27: SCALABILITY & CAPACITY
A28: 21 | B28: Scalability & Capacity | C28: SC-01 | D28: Our firm's service delivery model is designed to scale — meaning we can serve significantly more clients at current quality levels without proportional increases in headcount or cost. | E28: Scalable service models create leverage. Firms where each new client requires equivalent new capacity face linear cost growth that limits profitability at scale. | H28: =IF(AND(F28<>"",G28<>""),ABS(G28-F28),"")
A29: 22 | B29: Scalability & Capacity | C29: SC-02 | D29: We have identified and addressed the key operational bottlenecks that currently limit our growth capacity, and we have plans to expand throughput in constraining areas. | E29: Bottleneck awareness prevents growth plateau. Firms that grow into unaddressed constraints experience service quality degradation that damages client relationships and advisor morale. | H29: =IF(AND(F29<>"",G29<>""),ABS(G29-F29),"")
A30: 23 | B30: Scalability & Capacity | C30: SC-03 | D30: Our technology systems are cloud-based, scalable, and configured to support substantially more users, data volume, and transaction throughput than we currently require. | E30: Technology headroom enables growth without disruption. Firms that hit technology limits during growth face expensive, disruptive migration projects at the worst possible time. | H30: =IF(AND(F30<>"",G30<>""),ABS(G30-F30),"")
A31: 24 | B31: Scalability & Capacity | C31: SC-04 | D31: We have a talent acquisition pipeline and onboarding capability that allows us to recruit, hire, and develop qualified advisors and support staff in alignment with our growth trajectory. | E31: Talent pipeline determines human capital growth capacity. Firms that cannot attract and develop quality professionals hit growth ceilings regardless of market opportunity. | H31: =IF(AND(F31<>"",G31<>""),ABS(G31-F31),"")
A32: 25 | B32: Scalability & Capacity | C32: SC-05 | D32: Our compliance infrastructure can accommodate growth in client count, advisor headcount, and geographic expansion without requiring fundamental regulatory restructuring. | E32: Compliance scalability prevents regulatory growth barriers. Firms that outgrow their compliance infrastructure face costly restructuring or geographic limitations that constrain expansion. | H32: =IF(AND(F32<>"",G32<>""),ABS(G32-F32),"")
A33: 26 | B33: Scalability & Capacity | C33: SC-06 | D33: We have established standardized processes and templates that maintain consistent service quality as our team expands, reducing dependency on any single individual's expertise or judgment. | E33: Process standardization enables quality at scale. Firms where service quality depends on individual brilliance rather than systematic processes face quality variance as they grow. | H33: =IF(AND(F33<>"",G33<>""),ABS(G33-F33),"")
A34: 27 | B34: Scalability & Capacity | C34: SC-07 | D34: Our physical and virtual office infrastructure can support significant team growth — including workspace, equipment, communication systems, and collaboration tools. | E34: Infrastructure capacity planning prevents operational friction during growth. Firms that address workspace and tools proactively maintain team productivity through expansion. | H34: =IF(AND(F34<>"",G34<>""),ABS(G34-F34),"")
A35: 28 | B35: Scalability & Capacity | C35: SC-08 | D35: We have financial modeling and forecasting capabilities that allow us to project the impact of growth scenarios on profitability, cash flow, and resource requirements. | E35: Growth modeling enables informed resource allocation. Firms that can project growth economics make better decisions about when, where, and how much to invest in expansion. | H35: =IF(AND(F35<>"",G35<>""),ABS(G35-F35),"")
A36: 29 | B36: Scalability & Capacity | C36: SC-09 | D36: Our leadership team has the bandwidth and capability to manage a significantly larger organization — including more direct reports, broader geographic footprint, and greater operational complexity. | E36: Leadership capacity is often the binding constraint on growth. Firms where leaders are already at capacity face organizational effectiveness decline as growth demands increase. | H36: =IF(AND(F36<>"",G36<>""),ABS(G36-F36),"")
A37: 30 | B37: Scalability & Capacity | C37: SC-10 | D37: We have established partnerships with outsourcing providers, technology vendors, and service partners that can flex to support varying levels of growth demand. | E37: Flexible partner capacity provides growth elasticity. Firms with scalable partner relationships can expand capacity quickly without the fixed costs of permanent infrastructure. | H37: =IF(AND(F37<>"",G37<>""),ABS(G37-F37),"")
A38: DIGITAL & MARKETING READINESS
A39: 31 | B39: Digital & Marketing Readiness | C39: DM-01 | D39: Our firm maintains a professional, up-to-date website that clearly communicates our value proposition, showcases our expertise, and provides prospective clients with a clear path to engagement. | E39: Website quality is the digital first impression. Prospective clients who find outdated or unclear websites frequently disengage before ever making contact, representing invisible lost opportunity. | H39: =IF(AND(F39<>"",G39<>""),ABS(G39-F39),"")
A40: 32 | B40: Digital & Marketing Readiness | C40: DM-02 | D40: We actively create and distribute original content — such as blog posts, market commentary, educational articles, or newsletters — that demonstrates our expertise and keeps our firm visible to prospects. | E40: Content creation establishes expertise and maintains visibility. Firms with consistent content programs generate more inbound interest and build stronger credibility with prospective clients. | H40: =IF(AND(F40<>"",G40<>""),ABS(G40-F40),"")
A41: 33 | B41: Digital & Marketing Readiness | C41: DM-03 | D41: Our firm has an active and professional presence on relevant social media platforms where our target clients spend time, and we engage authentically rather than simply broadcasting. | E41: Social media presence extends reach and builds familiarity. Firms that engage authentically on social platforms create awareness and trust that traditional marketing cannot replicate. | H41: =IF(AND(F41<>"",G41<>""),ABS(G41-F41),"")
A42: 34 | B42: Digital & Marketing Readiness | C42: DM-04 | D42: We leverage digital marketing tools including email automation, CRM-driven workflows, and targeted outreach campaigns that nurture prospective clients through the engagement journey. | E42: Marketing automation enables scalable, personalized prospect nurturing. Firms that automate routine marketing touches maintain prospect engagement without consuming advisor time. | H42: =IF(AND(F42<>"",G42<>""),ABS(G42-F42),"")
A43: 35 | B43: Digital & Marketing Readiness | C43: DM-05 | D43: Our firm tracks digital marketing performance metrics — including website traffic, content engagement, lead generation, and conversion rates — to optimize marketing investment and effectiveness. | E43: Marketing measurement enables marketing optimization. Firms that track digital performance can allocate marketing budget to highest-returning channels and eliminate unproductive spending. | H43: =IF(AND(F43<>"",G43<>""),ABS(G43-F43),"")
A44: 36 | B44: Digital & Marketing Readiness | C44: DM-06 | D44: We maintain a consistent brand identity across all digital and physical touchpoints — including website, social media, email communications, office environment, and client materials. | E44: Brand consistency builds professional credibility and recognition. Inconsistent branding creates confusion and undermines the trust that consistent professional presence builds over time. | H44: =IF(AND(F44<>"",G44<>""),ABS(G44-F44),"")
A45: 37 | B45: Digital & Marketing Readiness | C45: DM-07 | D45: Our firm has invested in search engine optimization (SEO) and local digital visibility strategies that ensure prospective clients in our target market can find us when searching for advisory services. | E45: Search visibility captures active demand. Prospective clients who search for advisory services and cannot find your firm choose competitors by default. | H45: =IF(AND(F45<>"",G45<>""),ABS(G45-F45),"")
A46: 38 | B46: Digital & Marketing Readiness | C46: DM-08 | D46: We provide prospective clients with a compelling digital experience — including an informative website, accessible educational resources, and easy scheduling — that encourages them to take the next step. | E46: Digital prospect experience determines conversion rate. Firms with frictionless digital engagement convert more website visitors into client conversations. | H46: =IF(AND(F46<>"",G46<>""),ABS(G46-F46),"")
A47: 39 | B47: Digital & Marketing Readiness | C47: DM-09 | D47: Our firm has a defined marketing budget, calendar, and execution plan that ensures consistent marketing activity rather than sporadic campaigns driven by immediate need. | E47: Marketing discipline enables marketing effectiveness. Firms that market consistently build compound awareness; firms that market sporadically waste resources on restart costs. | H47: =IF(AND(F47<>"",G47<>""),ABS(G47-F47),"")
A48: 40 | B48: Digital & Marketing Readiness | C48: DM-10 | D48: We leverage client testimonials, case studies, or success stories (within compliance guidelines) to demonstrate real-world impact and build credibility with prospective clients. | E48: Social proof accelerates trust-building. Prospective clients who see evidence of real client outcomes develop confidence faster than those who rely solely on firm claims. | H48: =IF(AND(F48<>"",G48<>""),ABS(G48-F48),"")
A49: STRATEGIC GROWTH VISION
A50: 41 | B50: Strategic Growth Vision | C50: GV-01 | D50: Our firm has a clearly articulated 3-5 year growth vision with specific revenue, client count, and AUM targets that are known and supported by the entire leadership team. | E50: Shared growth vision aligns effort and resource allocation. Firms where leaders disagree on growth targets or ambition level waste energy on internal alignment rather than external execution. | H50: =IF(AND(F50<>"",G50<>""),ABS(G50-F50),"")
A51: 42 | B51: Strategic Growth Vision | C51: GV-02 | D51: We have identified specific market segments, service niches, or geographic territories where we believe our firm has the strongest growth opportunity and competitive advantage. | E51: Market focus concentrates growth effort on highest-probability opportunities. Firms that try to grow everywhere grow nowhere effectively. | H51: =IF(AND(F51<>"",G51<>""),ABS(G51-F51),"")
A52: 43 | B52: Strategic Growth Vision | C52: GV-03 | D52: Our firm has a clear strategy for balancing organic growth (new client acquisition) with inorganic growth (acquisitions and partnerships) based on our capabilities and market conditions. | E52: Growth pathway balance reflects strategic sophistication. Firms that rely exclusively on one growth method miss opportunities and are vulnerable to channel-specific disruptions. | H52: =IF(AND(F52<>"",G52<>""),ABS(G52-F52),"")
A53: 44 | B53: Strategic Growth Vision | C53: GV-04 | D53: We regularly evaluate our competitive positioning — including strengths, weaknesses, and differentiators — relative to other advisory firms in our market and use this intelligence to refine our growth strategy. | E53: Competitive awareness sharpens growth strategy. Firms that understand their competitive landscape make better decisions about where to invest growth resources. | H53: =IF(AND(F53<>"",G53<>""),ABS(G53-F53),"")
A54: 45 | B54: Strategic Growth Vision | C54: GV-05 | D54: Our firm's compensation and incentive structure is designed to attract growth-oriented talent and reward behaviors that drive sustainable revenue growth and client acquisition. | E54: Growth-aligned compensation attracts and motivates growth talent. Firms that reward only service delivery rather than growth activity struggle to develop business development capability. | H54: =IF(AND(F54<>"",G54<>""),ABS(G54-F54),"")
A55: 46 | B55: Strategic Growth Vision | C55: GV-06 | D55: We have established strategic partnerships or alliances — such as custodial relationships, technology partnerships, or professional networks — that create competitive advantages and growth enablers. | E55: Strategic partnerships multiply growth capability. Firms that leverage partnership ecosystems access resources, referrals, and capabilities that would be expensive to build independently. | H55: =IF(AND(F55<>"",G55<>""),ABS(G55-F55),"")
A56: 47 | B56: Strategic Growth Vision | C56: GV-07 | D56: Our firm evaluates new service offerings, client segments, or revenue models on a regular basis to ensure we are capturing evolving market opportunities and client needs. | E56: Service innovation maintains competitive relevance. Firms that rely on static service models face gradual market share erosion as client expectations and competitive offerings evolve. | H56: =IF(AND(F56<>"",G56<>""),ABS(G56-F56),"")
A57: 48 | B57: Strategic Growth Vision | C57: GV-08 | D57: We have a clear understanding of the client experience from first contact through onboarding to ongoing service, and we continuously refine this journey to maximize client satisfaction and referral generation. | E57: Client experience optimization drives retention and referral growth simultaneously. Firms that invest in journey mapping and continuous improvement create compounding growth advantages. | H57: =IF(AND(F57<>"",G57<>""),ABS(G57-F57),"")
A58: 49 | B58: Strategic Growth Vision | C58: GV-09 | D58: Our firm actively invests in innovation — whether through new technology adoption, service model evolution, or process improvement — as a growth strategy rather than just a cost management tool. | E58: Innovation as growth strategy creates differentiation. Firms that innovate proactively attract forward-thinking clients and talent that fuel continued growth momentum. | H58: =IF(AND(F58<>"",G58<>""),ABS(G58-F58),"")
A59: 50 | B59: Strategic Growth Vision | C59: GV-10 | D59: We have established a growth accountability framework where specific team members own growth metrics, report progress regularly, and are empowered to make decisions that advance growth objectives. | E59: Growth accountability converts aspiration into execution. Without clear ownership and regular reporting, growth initiatives drift and resources are consumed by operational demands. | H59: =IF(AND(F59<>"",G59<>""),ABS(G59-F59),"")

Sheet Scoring Engine
A1: SCORING ENGINE — GROWTH READINESS
A3: Growth Dimension | B3: Avg Current State | C3: Avg Growth Target | D3: Avg Growth Gap | E3: Growth Alignment % | F3: Readiness Score (0-100) | G3: SWOT Classification
A4: Organic Growth Engine | B4: =IFERROR(AVERAGE(Questions!F6:F15),"") | C4: =IFERROR(AVERAGE(Questions!G6:G15),"") | D4: =IFERROR(AVERAGE(Questions!H6:H15),"") | E4: =IFERROR((1-D4/4)*100,"") | F4: =IFERROR(B4/5*100,"") | G4: =IFERROR(IF(E4>=90,"STRENGTH",IF(E4>=75,"OPPORTUNITY",IF(E4>=60,"THREAT","WEAKNESS"))),"") -> STRENGTH
A5: Inorganic Growth Capability | B5: =IFERROR(AVERAGE(Questions!F17:F26),"") | C5: =IFERROR(AVERAGE(Questions!G17:G26),"") | D5: =IFERROR(AVERAGE(Questions!H17:H26),"") | E5: =IFERROR((1-D5/4)*100,"") | F5: =IFERROR(B5/5*100,"") | G5: =IFERROR(IF(E5>=90,"STRENGTH",IF(E5>=75,"OPPORTUNITY",IF(E5>=60,"THREAT","WEAKNESS"))),"") -> STRENGTH
A6: Scalability & Capacity | B6: =IFERROR(AVERAGE(Questions!F28:F37),"") | C6: =IFERROR(AVERAGE(Questions!G28:G37),"") | D6: =IFERROR(AVERAGE(Questions!H28:H37),"") | E6: =IFERROR((1-D6/4)*100,"") | F6: =IFERROR(B6/5*100,"") | G6: =IFERROR(IF(E6>=90,"STRENGTH",IF(E6>=75,"OPPORTUNITY",IF(E6>=60,"THREAT","WEAKNESS"))),"") -> STRENGTH
A7: Digital & Marketing Readiness | B7: =IFERROR(AVERAGE(Questions!F39:F48),"") | C7: =IFERROR(AVERAGE(Questions!G39:G48),"") | D7: =IFERROR(AVERAGE(Questions!H39:H48),"") | E7: =IFERROR((1-D7/4)*100,"") | F7: =IFERROR(B7/5*100,"") | G7: =IFERROR(IF(E7>=90,"STRENGTH",IF(E7>=75,"OPPORTUNITY",IF(E7>=60,"THREAT","WEAKNESS"))),"") -> STRENGTH
A8: Strategic Growth Vision | B8: =IFERROR(AVERAGE(Questions!F50:F59),"") | C8: =IFERROR(AVERAGE(Questions!G50:G59),"") | D8: =IFERROR(AVERAGE(Questions!H50:H59),"") | E8: =IFERROR((1-D8/4)*100,"") | F8: =IFERROR(B8/5*100,"") | G8: =IFERROR(IF(E8>=90,"STRENGTH",IF(E8>=75,"OPPORTUNITY",IF(E8>=60,"THREAT","WEAKNESS"))),"") -> STRENGTH
A11: OVERALL GROWTH READINESS SCORES
A12: Overall Growth Readiness Score | B12: =IFERROR(AVERAGE(F4:F8),"")
A13: Overall Growth Gap | B13: =IFERROR(AVERAGE(D4:D8),"")
A14: Overall Growth Alignment % | B14: =IFERROR(AVERAGE(E4:E8),"")
A15: Total Questions Answered | B15: =COUNTA(Questions!F6:F59) -> 0
A16: Strengths Count | B16: =COUNTIF(G4:G8,"STRENGTH") -> 5
A17: Opportunities Count | B17: =COUNTIF(G4:G8,"OPPORTUNITY") -> 0
A18: Threats Count | B18: =COUNTIF(G4:G8,"THREAT") -> 0
A19: Weaknesses Count | B19: =COUNTIF(G4:G8,"WEAKNESS") -> 0
A21: GROWTH READINESS TIER CLASSIFICATION
A22: 90-100: Growth Accelerator | B22: Firm is positioned for aggressive, confident growth execution
A23: 75-89: Growth Ready | B23: Strong growth foundations with targeted capability gaps to address
A24: 60-74: Growth Building | B24: Active growth capability development with meaningful areas of investment needed
A25: 40-59: Growth Emerging | B25: Early-stage growth infrastructure requiring significant development
A26: Below 40: Pre-Growth | B26: Foundational growth capabilities need to be established before growth execution

Sheet SWOT Narratives
A1: SWOT NARRATIVE FEEDBACK — GROWTH READINESS
A3: Growth Dimension | B3: SWOT Class | C3: Narrative Feedback
A4: Organic Growth Engine | B4: STRENGTH | C4: Your organic growth engine is firing on all cylinders. Systematic client acquisition, strong retention metrics, referral culture, and disciplined client selection create a compounding growth machine. Your organic growth infrastructure represents a significant competitive advantage and a strong foundation for sustainable expansion. Continue optimizing conversion rates and deepening client relationships.
A5: Organic Growth Engine | B5: OPPORTUNITY | C5: Your organic growth foundations are solid with specific areas for enhancement. Core elements like client acquisition strategy, retention management, or referral generation may be strong while others need development. Targeted investment in the weaker organic growth elements could meaningfully accelerate your growth trajectory. Focus on systematizing the elements that currently rely on individual effort.
A6: Organic Growth Engine | B6: THREAT | C6: Your organic growth capability has meaningful gaps that limit growth potential. Issues like inconsistent client acquisition, weak referral generation, or unclear ideal client definition constrain your ability to grow predictably. We recommend a comprehensive organic growth audit to identify the highest-leverage improvement opportunities.
A7: Organic Growth Engine | B7: WEAKNESS | C7: Your organic growth infrastructure requires substantial development. Without systematic acquisition processes, client retention strategies, and referral programs, organic growth depends on serendipity rather than strategy. We recommend establishing foundational organic growth systems before investing in other growth initiatives.
A8: Inorganic Growth Capability | B8: STRENGTH | C8: Your inorganic growth capability is excellent. Clear acquisition criteria, financial capacity, integration expertise, and cultural assessment processes position you to execute acquisitions that create genuine value. This M&A readiness represents a significant strategic advantage in the current advisory firm consolidation landscape.
A9: Inorganic Growth Capability | B9: OPPORTUNITY | C9: Your inorganic growth foundations show promising development with specific capability gaps to address. Core elements like financial capacity or acquisition criteria may be strong while integration playbooks or deal pipeline cultivation need development. Targeted M&A capability investment could unlock significant growth acceleration.
A10: Inorganic Growth Capability | B10: THREAT | C10: Your inorganic growth capability has meaningful gaps that could lead to costly acquisition mistakes. Issues like limited integration experience, unclear criteria, or insufficient financial capacity create risk in M&A execution. We recommend engaging M&A advisory support and developing integration capability before pursuing acquisitions.
A11: Inorganic Growth Capability | B11: WEAKNESS | C11: Your inorganic growth infrastructure requires significant development before acquisitions are advisable. Without clear criteria, financial capacity, integration expertise, and cultural assessment processes, acquisitions risk value destruction rather than creation. We recommend foundational M&A education and capability development.
A12: Scalability & Capacity | B12: STRENGTH | C12: Your scalability infrastructure is excellent. Scalable service models, adequate technology capacity, talent pipelines, and leadership bandwidth create the infrastructure for confident growth execution. Your capacity to absorb growth without quality degradation is a significant competitive advantage.
A13: Scalability & Capacity | B13: OPPORTUNITY | C13: Your scalability foundations are solid with specific capacity constraints to address. Core infrastructure may support growth while specific bottlenecks — perhaps in talent acquisition, technology capacity, or leadership bandwidth — limit your growth ceiling. Identify and address the binding constraint to unlock the next growth tier.
A14: Scalability & Capacity | B14: THREAT | C14: Your scalability has meaningful limitations that will constrain growth if not addressed. Bottlenecks in operational capacity, technology infrastructure, talent pipeline, or leadership bandwidth will create growth plateaus or quality degradation. We recommend a comprehensive capacity assessment to identify and prioritize constraint removal.
... A23: Strategic Growth Vision | B23: WEAKNESS | C23: Your strategic growth framework requires substantial development. Without clear vision, focused strategy, competitive awareness, and accountability structures, growth efforts scatter across unfocused initiatives. We strongly recommend establishing foundational growth strategy before investing in growth execution activities.

Sheet Instructions
A1: CATHEDRAL CENTER — GROWTH READINESS ASSESSMENT
A2: Instructions & Methodology Guide
A4: PURPOSE
A5: This assessment evaluates your firm's readiness to execute growth strategies — both organic and inorganic — across five critical dimensions. The results identify specific growth capabilities, capacity constraints, and strategic development opportunities that inform your growth planning.
A7: FIVE GROWTH DIMENSIONS
A8: 1. Organic Growth Engine (10 questions) — Client acquisition, retention, referrals, thought leadership
A9: 2. Inorganic Growth Capability (10 questions) — M&A readiness, criteria, integration, cultural assessment
A10: 3. Scalability & Capacity (10 questions) — Operational scale, technology, talent, leadership bandwidth
A11: 4. Digital & Marketing Readiness (10 questions) — Web presence, content, social, automation, measurement
A12: 5. Strategic Growth Vision (10 questions) — Growth targets, market focus, competitive positioning, accountability
A14: GROWTH READINESS TIER CLASSIFICATION
A15: 90-100: Growth Accelerator — Positioned for aggressive growth execution
... A19: Below 40: Pre-Growth — Foundational capabilities need to be established
