Workbook

Sheet Questions
A1: CATHEDRAL CENTER — PRACTICE GAP ANALYSIS ASSESSMENT
A2: Tier 2 Self-Assessment | Measures Current State vs. Desired Future State Across 9 Practice Dimensions
A3: Response Scale: 1 = Not at all like our firm | 2 = Not much like our firm | 3 = Somewhat like our firm | 4 = Mostly like our firm | 5 = Exactly like our firm
A4: # | B4: DNA Category | C4: Code | D4: Assessment Statement | E4: Context & Guidance | F4: Current State (1-5) | G4: Desired State (1-5) | H4: Gap Score
A5: FINANCIAL STRUCTURE
A6: 1 | B6: Financial Structure | C6: FIN-01 | D6: Our firm operates primarily under a fee-based revenue model where the majority of our income is derived from advisory fees rather than transactional commissions. | E6: Revenue model alignment is foundational to partnership compatibility. Firms with fundamentally different revenue structures may face tension around client pricing, service bundling, and profitability expectations. | H6: =IF(AND(F6<>"",G6<>""),ABS(G6-F6),"")
A7: 2 | B7: Financial Structure | C7: FIN-02 | D7: We maintain clear visibility into our profit margins at both the firm level and the individual advisor level, and we actively manage toward profitability targets. | E7: Profit margin transparency and discipline indicate operational maturity. Partners who differ significantly on financial visibility may struggle with shared resource allocation and investment decisions. | H7: =IF(AND(F7<>"",G7<>""),ABS(G7-F7),"")
A8: 3 | B8: Financial Structure | C8: FIN-03 | D8: Our firm has diversified revenue streams beyond core advisory fees, including planning fees, consulting engagements, insurance solutions, or other complementary services. | E8: Revenue diversification reduces dependency on any single income source and can indicate strategic sophistication. Understanding a partner's revenue mix helps predict financial stability and growth trajectory. | H8: =IF(AND(F8<>"",G8<>""),ABS(G8-F8),"")
A9: 4 | B9: Financial Structure | C9: FIN-04 | D9: We have a clearly defined compensation structure for advisors and staff that is transparent, competitive, and aligned with firm growth objectives. | E9: Compensation philosophy shapes firm culture and talent retention. Misalignment here can create significant friction during integration, particularly around equity participation and performance incentives. | H9: =IF(AND(F9<>"",G9<>""),ABS(G9-F9),"")
A10: 5 | B10: Financial Structure | C10: FIN-05 | D10: Our firm maintains strong financial reserves and manages cash flow with enough runway to weather market downturns and invest in strategic growth initiatives. | E10: Financial stability and reserve discipline reflect long-term thinking. Partners with different cash management philosophies may disagree on investment timing, risk tolerance, and growth spending. | H10: =IF(AND(F10<>"",G10<>""),ABS(G10-F10),"")
A11: 6 | B11: Financial Structure | C11: FIN-06 | D11: We regularly review and benchmark our pricing structure against industry standards to ensure we are delivering appropriate value relative to the fees our clients pay. | E11: Fee discipline and value consciousness indicate client-centered thinking. Firms that approach pricing differently may face challenges aligning on service-to-fee ratios in a combined entity. | H11: =IF(AND(F11<>"",G11<>""),ABS(G11-F11),"")
A12: ASSET MANAGEMENT
A13: 7 | B13: Asset Management | C13: AM-01 | D13: Our investment management approach leans primarily toward active portfolio management, where we seek to outperform benchmarks through research-driven security selection and tactical allocation. | E13: Investment philosophy is one of the most fundamental compatibility factors. Active and passive approaches require different infrastructure, staffing, and client communication strategies. | H13: =IF(AND(F13<>"",G13<>""),ABS(G13-F13),"")
A14: 8 | B14: Asset Management | C14: AM-02 | D14: We utilize a model-based portfolio construction approach where client portfolios are built from a defined set of investment models rather than individually selected securities. | E14: Model-based vs. individual portfolio construction reflects scalability philosophy. Firms that differ here may struggle with combined operations, compliance oversight, and performance reporting. | H14: =IF(AND(F14<>"",G14<>""),ABS(G14-F14),"")
A15: 9 | B15: Asset Management | C15: AM-03 | D15: Our firm incorporates values-based, ESG, or socially conscious investment options as a standard offering within our client portfolios when aligned with client preferences. | E15: Values-based investing reflects both client demand responsiveness and firm conviction. Partners who differ significantly here may face challenges aligning investment menus and client messaging. | H15: =IF(AND(F15<>"",G15<>""),ABS(G15-F15),"")
A16: 10 | B16: Asset Management | C16: AM-04 | D16: We maintain access to a broad investment platform that includes alternative investments, private placements, or non-traditional asset classes beyond standard equities and fixed income. | E16: Platform depth indicates sophistication of investment offering and client complexity. Partners with different platform access may need to reconcile custodial relationships and due diligence processes. | H16: =IF(AND(F16<>"",G16<>""),ABS(G16-F16),"")
A17: 11 | B17: Asset Management | C17: AM-05 | D17: Our firm has a dedicated research capability or investment committee that actively evaluates investment opportunities and monitors portfolio performance on an ongoing basis. | E17: Research infrastructure reflects investment seriousness and scale. Partners who differ on research commitment may face tension around investment decision-making authority and accountability. | H17: =IF(AND(F17<>"",G17<>""),ABS(G17-F17),"")
A18: 12 | B18: Asset Management | C18: AM-06 | D18: We have clearly documented investment processes, including an Investment Policy Statement template, rebalancing protocols, and performance benchmarking standards for all client accounts. | E18: Process documentation indicates operational discipline in investment management. Partners without aligned documentation standards may face regulatory and compliance integration challenges. | H18: =IF(AND(F18<>"",G18<>""),ABS(G18-F18),"")
A19: FINANCIAL PLANNING
A20: 13 | B20: Financial Planning | C20: FP-01 | D20: Our firm delivers comprehensive financial planning as a core service, integrating retirement projections, tax planning, estate considerations, and risk management into a unified client deliverable. | E20: Financial planning depth defines client value proposition. Partners who differ on planning comprehensiveness may struggle to deliver consistent client experiences across a combined practice. | H20: =IF(AND(F20<>"",G20<>""),ABS(G20-F20),"")
A21: 14 | B21: Financial Planning | C21: FP-02 | D21: We incorporate behavioral finance principles into our planning process, helping clients recognize cognitive biases and emotional patterns that may affect their financial decision-making. | E21: Behavioral finance integration represents an emerging differentiator. Partners aligned here can create powerful combined offerings; those misaligned may debate resource allocation toward this capability. | H21: =IF(AND(F21<>"",G21<>""),ABS(G21-F21),"")
A22: 15 | B22: Financial Planning | C22: FP-03 | D22: Our planning approach emphasizes goals-based outcomes, where each financial recommendation is tied to specific client life goals rather than purely investment return metrics. | E22: Goals-based planning reflects client-centered philosophy. Partners who differ on planning philosophy may struggle to standardize deliverables and client communication in a combined entity. | H22: =IF(AND(F22<>"",G22<>""),ABS(G22-F22),"")
A23: 16 | B23: Financial Planning | C23: FP-04 | D23: We offer advanced planning services including business succession planning, charitable giving strategies, multi-generational wealth transfer, or executive compensation analysis. | E23: Advanced planning capability indicates service depth and client complexity. Partners with different planning capabilities may see an opportunity to expand combined offerings or may face capacity constraints. | H23: =IF(AND(F23<>"",G23<>""),ABS(G23-F23),"")
A24: 17 | B24: Financial Planning | C24: FP-05 | D24: Our firm utilizes a structured cash flow-based planning methodology where we analyze client income, expenses, savings patterns, and spending behaviors as the foundation of all financial recommendations. | E24: Cash flow planning methodology reflects practical, client-accessible planning philosophy. Partners who differ may face challenges integrating planning software and client reporting standards. | H24: =IF(AND(F24<>"",G24<>""),ABS(G24-F24),"")
A25: 18 | B25: Financial Planning | C25: FP-06 | D25: We actively incorporate insurance planning, including life, disability, long-term care, and property/casualty review, as a standard element of our comprehensive planning process. | E25: Insurance integration reflects holistic planning philosophy. Partners who differ on insurance inclusion may face product licensing, compliance, and revenue model alignment challenges. | H25: =IF(AND(F25<>"",G25<>""),ABS(G25-F25),"")
A26: INFRASTRUCTURE
A27: 19 | B27: Infrastructure | C27: INF-01 | D27: Our firm has dedicated operational support that handles account administration, trading operations, client onboarding, and service requests so advisors can focus primarily on client relationships. | E27: Operational support structure directly impacts advisor productivity and client experience. Partners who differ on support models may face significant workflow integration challenges. | H27: =IF(AND(F27<>"",G27<>""),ABS(G27-F27),"")
A28: 20 | B28: Infrastructure | C28: INF-02 | D28: We maintain a structured employee benefits package including health insurance, retirement plans, and professional development resources that helps attract and retain quality team members. | E28: Benefits infrastructure reflects investment in human capital. Partners with different benefits philosophies may face compensation integration complexity and potential talent retention risk. | H28: =IF(AND(F28<>"",G28<>""),ABS(G28-F28),"")
A29: 21 | B29: Infrastructure | C29: INF-03 | D29: Our firm operates within a framework that gives advisors meaningful independence in how they serve clients while maintaining firm-level oversight on compliance, branding, and operational standards. | E29: Independence vs. structure balance defines firm operating model. Partners with fundamentally different frameworks may face governance and decision-making authority challenges. | H29: =IF(AND(F29<>"",G29<>""),ABS(G29-F29),"")
A30: 22 | B30: Infrastructure | C30: INF-04 | D30: We have established relationships with outsourcing partners for key operational functions such as compliance monitoring, portfolio accounting, performance reporting, or marketing support. | E30: Outsourcing strategy reflects operational philosophy and cost management approach. Partners with different outsourcing models may need to renegotiate vendor relationships and service agreements. | H30: =IF(AND(F30<>"",G30<>""),ABS(G30-F30),"")
A31: 23 | B31: Infrastructure | C31: INF-05 | D31: Our firm has a clearly defined and documented client onboarding process that ensures consistent first impressions, thorough data gathering, and seamless account setup for every new relationship. | E31: Client onboarding consistency reflects operational discipline and client experience commitment. Partners who differ here may face service quality variance in a combined practice. | H31: =IF(AND(F31<>"",G31<>""),ABS(G31-F31),"")
A32: 24 | B32: Infrastructure | C32: INF-06 | D32: We provide virtual or remote operational support capabilities that allow our team and clients to work effectively regardless of physical location or office presence. | E32: Virtual capability reflects modern operational readiness. Partners with different remote work philosophies may face culture and productivity expectation misalignment. | H32: =IF(AND(F32<>"",G32<>""),ABS(G32-F32),"")
A33: TECHNOLOGY
A34: 25 | B34: Technology | C34: TECH-01 | D34: Our firm operates with an integrated technology stack where our CRM, financial planning software, portfolio management system, and client portal share data with minimal manual entry. | E34: Technology integration level directly impacts efficiency, data accuracy, and client experience quality. Partners with different tech maturity may face significant systems integration costs. | H34: =IF(AND(F34<>"",G34<>""),ABS(G34-F34),"")
A35: 26 | B35: Technology | C35: TECH-02 | D35: We have a high-quality CRM system that is actively used by all team members for client relationship management, task tracking, workflow automation, and business intelligence reporting. | E35: CRM adoption and quality indicate operational discipline and data-driven management. Partners who differ on CRM usage may face challenges unifying client data and relationship history. | H35: =IF(AND(F35<>"",G35<>""),ABS(G35-F35),"")
A36: 27 | B36: Technology | C36: TECH-03 | D36: Our firm provides clients with a modern digital portal experience where they can access account information, documents, reports, and communication tools through a secure online interface. | E36: Client portal quality reflects technology commitment and client experience investment. Partners with different portal capabilities may need to standardize digital experiences post-integration. | H36: =IF(AND(F36<>"",G36<>""),ABS(G36-F36),"")
A37: 28 | B37: Technology | C37: TECH-04 | D37: We leverage technology for advisor-facing workflows including performance dashboards, compliance monitoring tools, and productivity applications that enhance daily operational efficiency. | E37: Advisor technology experience impacts productivity, job satisfaction, and competitive positioning. Partners with different advisor tool quality may face retention risk during integration. | H37: =IF(AND(F37<>"",G37<>""),ABS(G37-F37),"")
A38: 29 | B38: Technology | C38: TECH-05 | D38: Our technology systems support bidirectional data flow, meaning information entered in one system automatically updates across all connected platforms without duplicate data entry. | E38: Data bidirectionality indicates technology sophistication and operational efficiency. Partners with different data flow maturity may face data integrity challenges during integration. | H38: =IF(AND(F38<>"",G38<>""),ABS(G38-F38),"")
A39: 30 | B39: Technology | C39: TECH-06 | D39: We have a defined technology investment strategy with a regular evaluation cycle for upgrading, replacing, or adding tools to our technology ecosystem based on firm and client needs. | E39: Technology strategy discipline indicates forward-thinking operational management. Partners with different investment philosophies may disagree on timing and priority of tech spending. | H39: =IF(AND(F39<>"",G39<>""),ABS(G39-F39),"")
A40: STRATEGY
A41: 31 | B41: Strategy | C41: STR-01 | D41: Our firm engages in regular strategic planning sessions where we define specific growth objectives, resource allocation priorities, and measurable milestones with defined timelines. | E41: Strategic planning discipline indicates organizational maturity and intentional growth. Partners who differ on planning rigor may face tension around goal-setting and accountability. | H41: =IF(AND(F41<>"",G41<>""),ABS(G41-F41),"")
A42: 32 | B42: Strategy | C42: STR-02 | D42: We have a clear and differentiated brand identity that communicates our unique value proposition, and we actively invest in maintaining and evolving that brand presence in our market. | E42: Brand identity clarity and investment indicate market positioning sophistication. Partners with strong but different brand identities may face challenging integration decisions. | H42: =IF(AND(F42<>"",G42<>""),ABS(G42-F42),"")
A43: 33 | B43: Strategy | C43: STR-03 | D43: Our firm actively pursues digital marketing strategies including content creation, social media presence, website optimization, and search visibility to attract prospective clients. | E43: Digital marketing engagement indicates modern client acquisition approach. Partners with different marketing philosophies may need to align on combined marketing strategy and budget. | H43: =IF(AND(F43<>"",G43<>""),ABS(G43-F43),"")
A44: 34 | B44: Strategy | C44: STR-04 | D44: We have established structured lead generation and client acquisition programs, including referral partnerships, center-of-influence networks, or institutional channel relationships. | E44: Client acquisition infrastructure indicates growth engine maturity. Partners who differ on acquisition strategy may see opportunity for combined growth or may face resource allocation debates. | H44: =IF(AND(F44<>"",G44<>""),ABS(G44-F44),"")
A45: 35 | B45: Strategy | C45: STR-05 | D45: Our firm has defined a clear succession plan that addresses ownership transition, client relationship continuity, and leadership development to ensure long-term business sustainability. | E45: Succession planning indicates long-term strategic thinking and responsible business stewardship. Partners without aligned succession thinking may face future governance challenges. | H45: =IF(AND(F45<>"",G45<>""),ABS(G45-F45),"")
A46: 36 | B46: Strategy | C46: STR-06 | D46: We actively evaluate opportunities for inorganic growth through acquisitions, mergers, or strategic partnerships as part of our ongoing business development strategy. | E46: Inorganic growth appetite indicates strategic ambition and deal capability. Partners with different growth appetites may face pace and risk tolerance misalignment. | H46: =IF(AND(F46<>"",G46<>""),ABS(G46-F46),"")
A47: CULTURE
A48: 37 | B48: Culture | C48: CUL-01 | D48: Our firm has a clearly articulated vision for the future that serves as a guiding framework for strategic decisions, team alignment, and long-term resource allocation. | E48: Shared vision clarity indicates organizational alignment and purpose-driven leadership. Partners with different visions may face fundamental direction disagreements. | H48: =IF(AND(F48<>"",G48<>""),ABS(G48-F48),"")
A49: 38 | B49: Culture | C49: CUL-02 | D49: We foster an entrepreneurial culture where team members are encouraged to take initiative, propose new ideas, and experiment with innovative approaches to serving clients. | E49: Entrepreneurial culture reflects innovation tolerance and empowerment philosophy. Partners with different cultures may face tension between structure and creative freedom. | H49: =IF(AND(F49<>"",G49<>""),ABS(G49-F49),"")
A50: 39 | B50: Culture | C50: CUL-03 | D50: Our firm prioritizes transparent and frequent internal communication, ensuring all team members have visibility into firm performance, strategic direction, and important decisions. | E50: Communication transparency indicates trust-based management and organizational health. Partners with different communication cultures may face information-sharing friction during integration. | H50: =IF(AND(F50<>"",G50<>""),ABS(G50-F50),"")
A51: 40 | B51: Culture | C51: CUL-04 | D51: We invest meaningfully in employee development through structured training programs, mentorship opportunities, professional certifications, and career path clarity for all team members. | E51: Development investment indicates human capital commitment. Partners with different development philosophies may face talent expectations and retention approach misalignment. | H51: =IF(AND(F51<>"",G51<>""),ABS(G51-F51),"")
A52: 41 | B52: Culture | C52: CUL-05 | D52: Our firm measures success not only through financial metrics but also through client impact measures such as satisfaction scores, retention rates, referral frequency, and planning completion rates. | E52: Holistic success measurement indicates client-centered culture. Partners who differ on success metrics may face goal-setting and performance evaluation challenges. | H52: =IF(AND(F52<>"",G52<>""),ABS(G52-F52),"")
A53: 42 | B53: Culture | C53: CUL-06 | D53: We have a strong performance-oriented culture where individual and team contributions are recognized, rewarded, and aligned with firm-level growth objectives. | E53: Performance culture reflects accountability and meritocracy philosophy. Partners with different performance management approaches may face compensation and recognition alignment challenges. | H53: =IF(AND(F53<>"",G53<>""),ABS(G53-F53),"")
A54: VALUES
A55: 43 | B55: Values | C55: VAL-01 | D55: Faith, purpose, or a values-driven mission plays a meaningful role in how our firm operates, the clients we serve, and the decisions we make as a leadership team. | E55: Values-driven operation reflects deep organizational identity. Partners who differ on the role of values in business may face fundamental philosophical compatibility challenges. | H55: =IF(AND(F55<>"",G55<>""),ABS(G55-F55),"")
A56: 44 | B56: Values | C56: VAL-02 | D56: We place a high priority on work-life integration, maintaining healthy boundaries, and ensuring that our team members can sustain both professional excellence and personal wellbeing. | E56: Work-life philosophy shapes culture and retention. Partners with different boundary expectations may face team satisfaction and productivity approach misalignment. | H56: =IF(AND(F56<>"",G56<>""),ABS(G56-F56),"")
A57: 45 | B57: Values | C57: VAL-03 | D57: Our firm actively engages in community impact, philanthropic giving, or social responsibility initiatives as an expression of our core values and commitment to making a positive difference. | E57: Community engagement reflects organizational character. Partners with different community investment philosophies may need to align on shared impact priorities. | H57: =IF(AND(F57<>"",G57<>""),ABS(G57-F57),"")
A58: 46 | B58: Values | C58: VAL-04 | D58: Coaching, mentorship, and ongoing professional guidance are central to how we develop our advisors and business leaders, and we invest both time and resources into these growth relationships. | E58: Coaching investment indicates development culture and long-term thinking. Partners who differ on coaching value may face talent development approach misalignment. | H58: =IF(AND(F58<>"",G58<>""),ABS(G58-F58),"")
A59: 47 | B59: Values | C59: VAL-05 | D59: We value diversity of thought, background, and experience within our team, and we actively seek to build an inclusive environment that welcomes different perspectives. | E59: Diversity commitment reflects modern organizational values. Partners with different inclusion philosophies may face culture integration challenges. | H59: =IF(AND(F59<>"",G59<>""),ABS(G59-F59),"")
A60: 48 | B60: Values | C60: VAL-06 | D60: Building and maintaining deep, lasting relationships is a cornerstone of our firm culture — with clients, team members, strategic partners, and community stakeholders. | E60: Relationship depth reflects relational vs. transactional business philosophy. Partners who differ here may face client service approach and team culture misalignment. | H60: =IF(AND(F60<>"",G60<>""),ABS(G60-F60),"")
A61: BEHAVIORAL PROFILE
A62: 49 | B62: Behavioral Profile | C62: BEH-01 | D62: From a leadership perspective, our firm is primarily driven by a results-oriented, competitive mindset where decisive action and forward momentum are highly valued. | E62: Driver orientation indicates pace, decisiveness, and competitive intensity. Partners need to understand behavioral compatibility to predict leadership dynamics and decision-making friction. | H62: =IF(AND(F62<>"",G62<>""),ABS(G62-F62),"")
A63: 50 | B63: Behavioral Profile | C63: BEH-02 | D63: We approach business decisions with a highly analytical, data-driven methodology where thorough research, risk assessment, and evidence-based reasoning guide our choices. | E63: Analytical orientation indicates process discipline and risk awareness. Partners who differ on analysis depth may face pace and decisiveness tension. | H63: =IF(AND(F63<>"",G63<>""),ABS(G63-F63),"")
A64: 51 | B64: Behavioral Profile | C64: BEH-03 | D64: Our firm culture is characterized by a collaborative, relationship-centered approach where consensus-building, team harmony, and supportive communication are priorities. | E64: Amiable orientation indicates collaboration and harmony emphasis. Partners who differ may face communication style and conflict resolution challenges. | H64: =IF(AND(F64<>"",G64<>""),ABS(G64-F64),"")
A65: 52 | B65: Behavioral Profile | C65: BEH-04 | D65: We operate with an expressive, visionary energy where big-picture thinking, creative problem-solving, and inspiring our team and clients are central to how we lead. | E65: Expressive orientation indicates vision-casting and inspirational leadership style. Partners who differ may face communication style and strategic planning approach misalignment. | H65: =IF(AND(F65<>"",G65<>""),ABS(G65-F65),"")
A66: 53 | B66: Behavioral Profile | C66: BEH-05 | D66: Our firm demonstrates strong change orientation and adaptability, where we embrace evolving market conditions, regulatory changes, and client needs as opportunities rather than disruptions. | E66: Change orientation reflects adaptability and innovation tolerance. Partners who differ may face significant tension during integration when change is inevitable. | H66: =IF(AND(F66<>"",G66<>""),ABS(G66-F66),"")
A67: 54 | B67: Behavioral Profile | C67: BEH-06 | D67: We maintain a hands-on management approach where leadership stays closely connected to daily operations, client interactions, and team performance on an ongoing basis. | E67: Management involvement level indicates control preference and delegation philosophy. Partners who differ may face governance and decision authority challenges. | H67: =IF(AND(F67<>"",G67<>""),ABS(G67-F67),"")

Sheet Scoring Engine
A1: SCORING ENGINE — PRACTICE GAP ANALYSIS
A2: Automated calculations based on assessment responses
A4: DNA Category | B4: Avg Current State | C4: Avg Desired State | D4: Avg Gap Score | E4: Category Alignment % | F4: Readiness Score (0-100) | G4: SWOT Classification
A5: Financial Structure | B5: =IFERROR(AVERAGE(Questions!F6:F11),"") | C5: =IFERROR(AVERAGE(Questions!G6:G11),"") | D5: =IFERROR(AVERAGE(Questions!H6:H11),"") | E5: =IFERROR((1-D5/4)*100,"") | F5: =IFERROR(B5/5*100,"") | G5: =IFERROR(IF(E5>=90,"STRENGTH",IF(E5>=75,"OPPORTUNITY",IF(E5>=60,"THREAT","WEAKNESS"))),"") -> STRENGTH
A6: Asset Management | B6: =IFERROR(AVERAGE(Questions!F13:F18),"") | C6: =IFERROR(AVERAGE(Questions!G13:G18),"") | D6: =IFERROR(AVERAGE(Questions!H13:H18),"") | E6: =IFERROR((1-D6/4)*100,"") | F6: =IFERROR(B6/5*100,"") | G6: =IFERROR(IF(E6>=90,"STRENGTH",IF(E6>=75,"OPPORTUNITY",IF(E6>=60,"THREAT","WEAKNESS"))),"") -> STRENGTH
A7: Financial Planning | B7: =IFERROR(AVERAGE(Questions!F20:F25),"") | C7: =IFERROR(AVERAGE(Questions!G20:G25),"") | D7: =IFERROR(AVERAGE(Questions!H20:H25),"") | E7: =IFERROR((1-D7/4)*100,"") | F7: =IFERROR(B7/5*100,"") | G7: =IFERROR(IF(E7>=90,"STRENGTH",IF(E7>=75,"OPPORTUNITY",IF(E7>=60,"THREAT","WEAKNESS"))),"") -> STRENGTH
A8: Infrastructure | B8: =IFERROR(AVERAGE(Questions!F27:F32),"") | C8: =IFERROR(AVERAGE(Questions!G27:G32),"") | D8: =IFERROR(AVERAGE(Questions!H27:H32),"") | E8: =IFERROR((1-D8/4)*100,"") | F8: =IFERROR(B8/5*100,"") | G8: =IFERROR(IF(E8>=90,"STRENGTH",IF(E8>=75,"OPPORTUNITY",IF(E8>=60,"THREAT","WEAKNESS"))),"") -> STRENGTH
A9: Technology | B9: =IFERROR(AVERAGE(Questions!F34:F39),"") | C9: =IFERROR(AVERAGE(Questions!G34:G39),"") | D9: =IFERROR(AVERAGE(Questions!H34:H39),"") | E9: =IFERROR((1-D9/4)*100,"") | F9: =IFERROR(B9/5*100,"") | G9: =IFERROR(IF(E9>=90,"STRENGTH",IF(E9>=75,"OPPORTUNITY",IF(E9>=60,"THREAT","WEAKNESS"))),"") -> STRENGTH
A10: Strategy | B10: =IFERROR(AVERAGE(Questions!F41:F46),"") | C10: =IFERROR(AVERAGE(Questions!G41:G46),"") | D10: =IFERROR(AVERAGE(Questions!H41:H46),"") | E10: =IFERROR((1-D10/4)*100,"") | F10: =IFERROR(B10/5*100,"") | G10: =IFERROR(IF(E10>=90,"STRENGTH",IF(E10>=75,"OPPORTUNITY",IF(E10>=60,"THREAT","WEAKNESS"))),"") -> STRENGTH
A11: Culture | B11: =IFERROR(AVERAGE(Questions!F48:F53),"") | C11: =IFERROR(AVERAGE(Questions!G48:G53),"") | D11: =IFERROR(AVERAGE(Questions!H48:H53),"") | E11: =IFERROR((1-D11/4)*100,"") | F11: =IFERROR(B11/5*100,"") | G11: =IFERROR(IF(E11>=90,"STRENGTH",IF(E11>=75,"OPPORTUNITY",IF(E11>=60,"THREAT","WEAKNESS"))),"") -> STRENGTH
A12: Values | B12: =IFERROR(AVERAGE(Questions!F55:F60),"") | C12: =IFERROR(AVERAGE(Questions!G55:G60),"") | D12: =IFERROR(AVERAGE(Questions!H55:H60),"") | E12: =IFERROR((1-D12/4)*100,"") | F12: =IFERROR(B12/5*100,"") | G12: =IFERROR(IF(E12>=90,"STRENGTH",IF(E12>=75,"OPPORTUNITY",IF(E12>=60,"THREAT","WEAKNESS"))),"") -> STRENGTH
A13: Behavioral Profile | B13: =IFERROR(AVERAGE(Questions!F62:F67),"") | C13: =IFERROR(AVERAGE(Questions!G62:G67),"") | D13: =IFERROR(AVERAGE(Questions!H62:H67),"") | E13: =IFERROR((1-D13/4)*100,"") | F13: =IFERROR(B13/5*100,"") | G13: =IFERROR(IF(E13>=90,"STRENGTH",IF(E13>=75,"OPPORTUNITY",IF(E13>=60,"THREAT","WEAKNESS"))),"") -> STRENGTH
A15: OVERALL ASSESSMENT SCORES
A16: Overall Practice Alignment Score | B16: =IFERROR(AVERAGE(E5:E13),"")
A17: Overall Practice Readiness Score | B17: =IFERROR(AVERAGE(F5:F13),"")
A18: Overall Gap Score (Avg) | B18: =IFERROR(AVERAGE(D5:D13),"")
A19: Total Questions Answered | B19: =COUNTA(Questions!F6:F67) -> 0
A20: Strengths Count | B20: =COUNTIF(G5:G13,"STRENGTH") -> 9
A21: Opportunities Count | B21: =COUNTIF(G5:G13,"OPPORTUNITY") -> 0
A22: Threats Count | B22: =COUNTIF(G5:G13,"THREAT") -> 0
A23: Weaknesses Count | B23: =COUNTIF(G5:G13,"WEAKNESS") -> 0

Sheet SWOT Narratives
A1: SWOT NARRATIVE FEEDBACK — PRACTICE GAP ANALYSIS
A2: AI-ready narrative templates triggered by scoring thresholds
A4: DNA Category | B4: SWOT Class | C4: Narrative Feedback
A5: Financial Structure | B5: STRENGTH | C5: Your financial structures are well aligned, indicating strong compatibility in revenue model, profitability management, and compensation philosophy. This alignment provides a solid economic foundation for partnership. We recommend formalizing shared financial reporting standards early in any integration process and establishing joint profitability targets that leverage the combined entity's scale advantages.
A6: Financial Structure | B6: OPPORTUNITY | C6: Your financial structures show promising alignment with room for optimization. The areas of agreement outweigh the gaps, suggesting that focused dialogue around pricing philosophy, margin expectations, and compensation harmonization could quickly close remaining differences. Consider establishing a joint financial review cadence to build shared visibility and trust around economic management.
A7: Financial Structure | B7: THREAT | C7: There are notable gaps in your financial structure alignment that warrant careful attention. Differences in revenue model philosophy, profitability expectations, or compensation approaches can create friction during integration. We recommend a structured financial compatibility workshop to surface specific differences and evaluate whether compromise positions are feasible before proceeding further.
A8: Financial Structure | B8: WEAKNESS | C8: Your financial structure alignment presents significant challenges. Fundamental differences in how you approach revenue, profitability, pricing, or compensation can undermine even the best-intentioned partnership. We recommend engaging a neutral financial advisor to evaluate whether structural differences can be bridged or represent incompatible business models.
A9: Asset Management | B9: STRENGTH | C9: Your investment management philosophies and practices are highly compatible. This alignment in asset management approach, portfolio construction methodology, and research commitment creates a strong foundation for delivering consistent client outcomes in a combined practice. Focus on identifying the strongest elements from each firm's investment process to create an enhanced combined approach.
A10: Asset Management | B10: OPPORTUNITY | C10: Your asset management approaches show solid alignment with some productive differences that could strengthen a combined offering. The key is to identify where different investment perspectives complement rather than conflict. Consider establishing a combined investment committee framework that leverages the best research and portfolio construction capabilities from both firms.
A11: Asset Management | B11: THREAT | C11: Meaningful differences exist in your asset management approaches. Investment philosophy misalignment can directly impact client experience, compliance requirements, and operational efficiency. We recommend a detailed investment process comparison to identify specific areas of divergence and evaluate whether a unified approach or dual-track model is more appropriate.
A12: Asset Management | B12: WEAKNESS | C12: Your asset management approaches show fundamental differences that require serious consideration. Investment philosophy is one of the hardest areas to compromise on because it directly affects client outcomes and firm identity. We recommend honest evaluation of whether these differences represent complementary strengths or incompatible convictions.
A13: Financial Planning | B13: STRENGTH | C13: Your financial planning approaches are well aligned, reflecting shared commitment to planning depth, methodology, and client deliverable quality. This compatibility enables a consistent and potentially enhanced client planning experience in a combined entity. Focus on identifying best-in-class planning tools and processes from each firm to create a unified planning framework.
A14: Financial Planning | B14: OPPORTUNITY | C14: Your financial planning capabilities show meaningful alignment with opportunities to strengthen the combined offering. Differences in planning specialization or methodology can actually enhance the breadth of services available to clients. Consider mapping each firm's planning strengths to identify complementary capabilities that could differentiate the combined practice.
A15: Financial Planning | B15: THREAT | C15: Notable differences exist in your financial planning philosophies and capabilities. Planning methodology is a core client experience driver, and inconsistency here can confuse clients and dilute your value proposition. We recommend documenting each firm's planning process in detail and identifying specific integration points and potential friction areas.
... A40: Behavioral Profile | B40: WEAKNESS | C40: Your behavioral profiles show significant misalignment. Fundamental behavioral incompatibility — such as mismatched pace, communication styles, or control preferences — can undermine even the most strategically sound partnership. We strongly recommend professional behavioral compatibility assessment before proceeding.

Sheet Response Variables
A1: 5-VARIABLE RESPONSE NARRATIVES — BY ALIGNMENT LEVEL
A2: Variable 1 = Highest alignment (gap 0) → Variable 5 = Lowest alignment (gap 4)
A4: DNA Category | B4: Variable | C4: Narrative Response
A5: Financial Structure | B5: Variable 1 | C5: Exceptional alignment. Your financial structures are remarkably compatible — from revenue models to compensation philosophy. This level of economic alignment is uncommon and provides a powerful foundation for partnership. Continue to refine shared financial KPIs and establish transparent reporting rhythms.
A6: Financial Structure | B6: Variable 2 | C6: Strong alignment. Your financial approaches are well-matched with minor philosophical differences that healthy dialogue can resolve. Focus on clarifying expectations around margin targets, reinvestment priorities, and compensation evolution as you explore the partnership path.
A7: Financial Structure | B7: Variable 3 | C7: Moderate alignment. There are areas of financial agreement alongside meaningful differences. Neither your revenue model approach nor your profitability expectations are fully aligned. Invest time in understanding the 'why' behind each firm's financial decisions before evaluating compatibility.
A8: Financial Structure | B8: Variable 4 | C8: Limited alignment. Significant differences exist in your financial structure philosophies. Areas like compensation design, pricing strategy, or profitability expectations may require substantial compromise from one or both parties. Consider whether these gaps are bridgeable through negotiation.
A9: Financial Structure | B9: Variable 5 | C9: Minimal alignment. Your financial structures differ fundamentally. When firms disagree on how money flows — revenue models, fee structures, compensation, and profitability standards — it creates friction that permeates every operational decision. Honest assessment of these differences is essential before proceeding.
A10: Asset Management | B10: Variable 1 | C10: Exceptional alignment. You share a deep compatibility in investment philosophy, process, and commitment. This is rare and valuable — your clients would benefit from the combined investment expertise. Focus on documenting a unified investment framework that captures the best of both approaches.
A11: Asset Management | B11: Variable 2 | C11: Strong alignment. Your investment management approaches are well-matched with productive differences worth exploring. These distinctions may actually strengthen a combined offering. Discuss specific investment process elements to identify where collaboration creates enhanced capability.
A12: Asset Management | B12: Variable 3 | C12: Moderate alignment. Your investment approaches share some common ground but diverge in meaningful ways. Active vs. passive leanings, model construction preferences, or research commitment may differ. Explore whether a dual-track approach or philosophical compromise could work.
A13: Asset Management | B13: Variable 4 | C13: Limited alignment. Notable investment philosophy differences exist. When firms disagree on fundamental investment approach, it affects portfolio construction, client communication, performance expectations, and compliance requirements. Evaluate honestly whether unified investment management is feasible.
A14: Asset Management | B14: Variable 5 | C14: Minimal alignment. Your investment management philosophies are fundamentally different. This is one of the most difficult areas to compromise on because it directly impacts client outcomes and firm identity. Carefully consider whether these differences represent a dealbreaker.
A15: Financial Planning | B15: Variable 1 | C15: Exceptional alignment. Your planning philosophies, methodologies, and depth commitments are remarkably compatible. This creates an opportunity for a combined planning practice that delivers industry-leading client value. Focus on identifying the most effective planning tools and processes from each firm.
... A49: Behavioral Profile | B49: Variable 5 | C49: Minimal alignment. Your behavioral profiles show fundamental incompatibility. When leaders differ drastically in pace, directness, collaboration style, or control preferences, the daily experience of partnership becomes exhausting rather than energizing. Behavioral compatibility assessment is essential.

Sheet Instructions
A1: CATHEDRAL CENTER — PRACTICE GAP ANALYSIS ASSESSMENT
A2: Instructions & Methodology Guide
A4: PURPOSE
A5: This assessment measures alignment between a financial advisory firm's current operational reality and its desired future state across nine critical practice dimensions. The resulting gap analysis identifies specific areas of strength, opportunity, and concern that inform partnership compatibility and strategic development recommendations.
A7: HOW IT WORKS
A8: 1. Each question asks you to rate a statement about your firm's practices on a scale of 1 to 5.
A9: 2. You provide TWO ratings for each statement:
A10: • Current State: How accurately does this statement describe your firm TODAY?
A11: • Desired State: How much do you WANT this statement to be true of your firm?
A12: 3. The Gap Score is automatically calculated as the absolute difference between your desired and current state.
A14: RESPONSE SCALE
A15: 1 = Not at all like our firm — This statement does not describe our firm at all
... A56: • This assessment is designed for both self-evaluation and two-party compatibility analysis
